lastfm/__init__.py
lastfm/client.py
lastfm/exceptions.py
lastfm/objects.py
lastfm/requests.py
lastfm/testing.py
lastfmpy/__init__.py
lastfmpy/client.py
lastfmpy/exceptions.py
lastfmpy/objects.py
lastfmpy/request.py
lastfmpy/testing.py
lastfmpy-1.1.dist-info/LICENSE
lastfmpy-1.1.dist-info/METADATA
lastfmpy-1.1.dist-info/WHEEL
lastfmpy-1.1.dist-info/top_level.txt
lastfmpy-1.1.dist-info/RECORD
